{
  "buildFiles": [
    "F:\\tools\\flutter\\packages\\flutter_tools\\gradle\\src\\main\\groovy\\CMakeLists.txt"
  ],
  "cleanCommandsComponents": [
    [
      "D:\\Program\\Android\\SDK\\cmake\\3.22.1\\bin\\ninja.exe",
      "-C",
      "F:\\projekte\\homeApplicationsClient\\android\\app\\.cxx\\RelWithDebInfo\\4n1g3y6n\\armeabi-v7a",
      "clean"
    ]
  ],
  "buildTargetsCommandComponents": [
    "D:\\Program\\Android\\SDK\\cmake\\3.22.1\\bin\\ninja.exe",
    "-C",
    "F:\\projekte\\homeApplicationsClient\\android\\app\\.cxx\\RelWithDebInfo\\4n1g3y6n\\armeabi-v7a",
    "{LIST_OF_TARGETS_TO_BUILD}"
  ],
  "libraries": {},
  "toolchains": {
    "toolchain": {
      "cCompilerExecutable": "D:\\Program\\Android\\SDK\\ndk\\26.3.11579264\\toolchains\\llvm\\prebuilt\\windows-x86_64\\bin\\clang.exe",
      "cppCompilerExecutable": "D:\\Program\\Android\\SDK\\ndk\\26.3.11579264\\toolchains\\llvm\\prebuilt\\windows-x86_64\\bin\\clang++.exe"
    }
  },
  "cFileExtensions": [],
  "cppFileExtensions": []
}